aptosindexer/__init__.py
aptosindexer-0.0.1.dist-info/LICENSE
aptosindexer-0.0.1.dist-info/METADATA
aptosindexer-0.0.1.dist-info/WHEEL
aptosindexer-0.0.1.dist-info/top_level.txt
aptosindexer-0.0.1.dist-info/RECORD
