Metadata-Version: 2.1
Name: aptosindexer
Version: 0.0.1
Summary: Aptos Indexer
Author-email: Stephen Maldonado <PyAptosIndexer@StephenMaldonado.com>
Project-URL: github, https://github.com/StephenMal/PyAptosIndexer
Project-URL: github-issues, https://github.com/StephenMal/PyAptosIndexer/issues
Project-URL: author, https://stephenmaldonado.com
Classifier: Programming Language :: Python :: 3
Classifier: Development Status :: 1 - Planning
Classifier: License :: OSI Approved :: MIT License
Classifier: Operating System :: OS Independent
Requires-Python: >=3.8
License-File: LICENSE
